make_slice/__init__.py
make_slice-0.4.0.dist-info/LICENSE
make_slice-0.4.0.dist-info/METADATA
make_slice-0.4.0.dist-info/WHEEL
make_slice-0.4.0.dist-info/RECORD
