Metadata-Version: 2.3
Name: make-slice
Version: 0.4.0
Summary: Creates slice objects with clean syntax.
License: MIT
Author: pl
Author-email: 0x00.pl@gmail.com
Requires-Python: >=3.9
Classifier: License :: OSI Approved :: MIT License
Classifier: Programming Language :: Python :: 3
Classifier: Programming Language :: Python :: 3.9
Classifier: Programming Language :: Python :: 3.10
Classifier: Programming Language :: Python :: 3.11
Classifier: Programming Language :: Python :: 3.12
Classifier: Programming Language :: Python :: 3.13
